forwardbasespawner/__init__.py
forwardbasespawner/_version.py
forwardbasespawner/api_events.py
forwardbasespawner/api_list_servers.py
forwardbasespawner/api_setup_tunnel.py
forwardbasespawner/api_sshnode_restarted.py
forwardbasespawner/forward.py
forwardbasespawner/utils.py
jupyterhub_forwardbasespawner-2.1.0.dist-info/METADATA
jupyterhub_forwardbasespawner-2.1.0.dist-info/WHEEL
jupyterhub_forwardbasespawner-2.1.0.dist-info/licenses/LICENSE
jupyterhub_forwardbasespawner-2.1.0.dist-info/RECORD
