Metadata-Version: 2.4
Name: jupyterhub-forwardbasespawner
Version: 2.1.0
Summary: JupyterHub BaseSpawner class. Enables remote single-user server.
Author-email: Tim Kreuzer <t.kreuzer@fz-juelich.de>
License: BSD 3-Clause License
License-File: LICENSE
Keywords: jupyterhub,spawner
Requires-Python: >=3.9
Requires-Dist: escapism
Requires-Dist: jinja2
Requires-Dist: jupyterhub>=5.0.0
Requires-Dist: kubernetes
Requires-Dist: traitlets
Requires-Dist: urllib3
